click_require_creds/__init__.py
click_require_creds/_core.py
click_require_creds/_decorators.py
click_require_creds/_helpers.py
click_require_creds-0.0.1.dist-info/LICENSE
click_require_creds-0.0.1.dist-info/METADATA
click_require_creds-0.0.1.dist-info/WHEEL
click_require_creds-0.0.1.dist-info/top_level.txt
click_require_creds-0.0.1.dist-info/RECORD
