Metadata-Version: 2.1
Name: click-require-creds
Version: 0.0.1
Summary: Click decorator to handle credentials
Home-page: UNKNOWN
Author: Carlos Garcia
Author-email: cgarciaarano@yahoo.es
License: UNKNOWN
Platform: UNKNOWN
Requires-Python: >=3.6
Requires-Dist: Click (<8,>=7.1)
Requires-Dist: nttldict (>=0.0.2)
